{
	"info": {
		"_postman_id": "1b6b6727-7fcc-455b-805d-ff89bcf69674",
		"name": "Grocers-API",
		"schema": "https://schema.getpostman.com/json/collection/v2.1.0/collection.json",
		"_exporter_id": "13990870"
	},
	"item": [
		{
			"name": "New Request",
			"request": {
				"method": "GET",
				"header": [],
				"url": {
					"raw": "http://localhost:3000/",
					"protocol": "http",
					"host": [
						"localhost"
					],
					"port": "3000",
					"path": [
						""
					]
				}
			},
			"response": []
		},
		{
			"name": "/user/add",
			"request": {
				"method": "POST",
				"header": [],
				"body": {
					"mode": "raw",
					"raw": "{\r\n    \"name\": \"test user\",\r\n    \"password\": \"Password123\",\r\n    \"email\": \"user@test.com\"\r\n}",
					"options": {
						"raw": {
							"language": "json"
						}
					}
				},
				"url": {
					"raw": "http://localhost:3000/user/add",
					"protocol": "http",
					"host": [
						"localhost"
					],
					"port": "3000",
					"path": [
						"user",
						"add"
					]
				}
			},
			"response": []
		},
		{
			"name": "/user/login",
			"request": {
				"method": "POST",
				"header": [],
				"url": {
					"raw": "http://localhost:3000/user/login?email=user@test.com&password=Password12",
					"protocol": "http",
					"host": [
						"localhost"
					],
					"port": "3000",
					"path": [
						"user",
						"login"
					],
					"query": [
						{
							"key": "email",
							"value": "user@test.com"
						},
						{
							"key": "password",
							"value": "Password12"
						}
					]
				}
			},
			"response": []
		},
		{
			"name": "test http",
			"request": {
				"method": "POST",
				"header": [],
				"url": {
					"raw": "http://localhost:3000/?name=test&password=Password123",
					"protocol": "http",
					"host": [
						"localhost"
					],
					"port": "3000",
					"path": [
						""
					],
					"query": [
						{
							"key": "name",
							"value": "test"
						},
						{
							"key": "password",
							"value": "Password123"
						}
					]
				}
			},
			"response": []
		}
	]
}